{"chunk_definitions":[{"row":49,"row_count":1,"visible":true,"expansion_state":0,"options":{"engine":"r","label":"unnamed-chunk-1","dev":"png"},"document_id":"39F66E33","chunk_id":"ck7owd4ajkwsp","chunk_label":"unnamed-chunk-1"},{"row":68,"row_count":1,"visible":true,"expansion_state":0,"options":{"engine":"r","label":"unnamed-chunk-2","dev":"png"},"document_id":"39F66E33","chunk_id":"cf1o6ty3qslqq","chunk_label":"unnamed-chunk-2"},{"row":87,"row_count":1,"visible":true,"expansion_state":0,"options":{"engine":"r","label":"unnamed-chunk-3","dev":"png"},"document_id":"39F66E33","chunk_id":"c958emz4ojufr","chunk_label":"unnamed-chunk-3"},{"row":99,"row_count":1,"visible":true,"expansion_state":0,"options":{"engine":"r","label":"unnamed-chunk-4","dev":"png"},"document_id":"39F66E33","chunk_id":"cmc64sr2k4y1c","chunk_label":"unnamed-chunk-4"},{"row":127,"row_count":1,"visible":true,"expansion_state":0,"options":{"engine":"r","label":"unnamed-chunk-5","dev":"png"},"document_id":"39F66E33","chunk_id":"ch9vx67d6aqqe","chunk_label":"unnamed-chunk-5"},{"row":149,"row_count":1,"visible":true,"expansion_state":0,"options":{"engine":"r","label":"unnamed-chunk-6","dev":"png"},"document_id":"39F66E33","chunk_id":"c5shzg5zvi34m","chunk_label":"unnamed-chunk-6"},{"row":175,"row_count":1,"visible":true,"expansion_state":0,"options":{"engine":"r","label":"unnamed-chunk-7","dev":"png"},"document_id":"39F66E33","chunk_id":"c9kz205v0uwvc","chunk_label":"unnamed-chunk-7"},{"row":190,"row_count":1,"visible":true,"expansion_state":0,"options":{"engine":"r","label":"unnamed-chunk-8","dev":"png"},"document_id":"39F66E33","chunk_id":"c30laawmaooyw","chunk_label":"unnamed-chunk-8"},{"row":197,"row_count":1,"visible":true,"expansion_state":0,"options":{"engine":"r","label":"unnamed-chunk-9","dev":"png"},"document_id":"39F66E33","chunk_id":"cphemy4f8pb73","chunk_label":"unnamed-chunk-9"},{"row":208,"row_count":1,"visible":true,"expansion_state":0,"options":{"engine":"r","label":"unnamed-chunk-10","dev":"png"},"document_id":"39F66E33","chunk_id":"cat1hcgcpfjhu","chunk_label":"unnamed-chunk-10"},{"row":217,"row_count":1,"visible":true,"expansion_state":0,"options":{"engine":"r","label":"unnamed-chunk-11","dev":"png"},"document_id":"39F66E33","chunk_id":"cx99xboozwmpq","chunk_label":"unnamed-chunk-11"},{"row":233,"row_count":1,"visible":true,"expansion_state":0,"options":{"engine":"r","label":"unnamed-chunk-12","dev":"png"},"document_id":"39F66E33","chunk_id":"c05m05b04vb07","chunk_label":"unnamed-chunk-12"},{"row":260,"row_count":1,"visible":true,"expansion_state":0,"options":{"engine":"r","label":"unnamed-chunk-13","dev":"png"},"document_id":"39F66E33","chunk_id":"c483v9sxs6537","chunk_label":"unnamed-chunk-14"}],"doc_write_time":1750070823}